secplugs.py
secplugs_python_client-0.1.dist-info/LICENSE
secplugs_python_client-0.1.dist-info/METADATA
secplugs_python_client-0.1.dist-info/WHEEL
secplugs_python_client-0.1.dist-info/top_level.txt
secplugs_python_client-0.1.dist-info/RECORD
